aiopyfcm/__init__.py
aiopyfcm/aiopyfcm.py
aiopyfcm/authenticator.py
aiopyfcm/errors.py
aiopyfcm/message.py
aiopyfcm-0.2.1.dist-info/LICENSE
aiopyfcm-0.2.1.dist-info/METADATA
aiopyfcm-0.2.1.dist-info/WHEEL
aiopyfcm-0.2.1.dist-info/top_level.txt
aiopyfcm-0.2.1.dist-info/RECORD
